LICENSE
README.md
setup.py
scripts/build-fasta-index
scripts/tmvec-build-database
scripts/tmvec-search
tm_vec/__init__.py
tm_vec/config.py
tm_vec/data_embed_structure.py
tm_vec/embed_structure_model.py
tm_vec/fasta.py
tm_vec/tm_vec_utils.py
tm_vec/train_embed_structure_model.py
tm_vec/utils.py
tm_vec.egg-info/PKG-INFO
tm_vec.egg-info/SOURCES.txt
tm_vec.egg-info/dependency_links.txt
tm_vec.egg-info/requires.txt
tm_vec.egg-info/top_level.txt